knoxth/__init__.py
knoxth/apps.py
knoxth/auth.py
knoxth/constants.py
knoxth/decorators.py
knoxth/fields.py
knoxth/mixins.py
knoxth/models.py
knoxth/serializers.py
knoxth/tests.py
knoxth/urls.py
knoxth/views.py
knoxth/migrations/0001_initial.py
knoxth/migrations/0002_claim.py
knoxth/migrations/0003_auto_20210510_0445.py
knoxth/migrations/0004_auto_20210513_0855.py
knoxth/migrations/0005_auto_20210515_0950.py
knoxth/migrations/0006_auto_20210515_1322.py
knoxth/migrations/0007_claim_name.py
knoxth/migrations/0008_auto_20210523_0634.py
knoxth/migrations/__init__.py
knoxth/mods/__init__.py
knoxth/mods/claim.py
knoxth/mods/context.py
knoxth/mods/scope.py
knoxth-0.0.3.dist-info/LICENSE
knoxth-0.0.3.dist-info/METADATA
knoxth-0.0.3.dist-info/WHEEL
knoxth-0.0.3.dist-info/top_level.txt
knoxth-0.0.3.dist-info/RECORD
