Metadata-Version: 2.1
Name: knoxth
Version: 0.0.3
Summary: Knoxth uses Knox tokens to provide token-level authorization management for DRF viewsets
Home-page: https://gitlab.com/ayys
Author: Ayush Jha
Author-email: ayushjha@protonmail.com
License: GPL-3.0
Keywords: drf,authorization,tokenauthorization,knox,scope
Platform: UNKNOWN
Classifier: Development Status :: 3 - Alpha
Classifier: Intended Audience :: Developers
Classifier: Topic :: Internet :: WWW/HTTP :: Session
Classifier: License :: OSI Approved :: GNU General Public License v3 or later (GPLv3+)
Classifier: Programming Language :: Python :: 3
Classifier: Programming Language :: Python :: 3.6
Classifier: Programming Language :: Python :: 3.7
Classifier: Programming Language :: Python :: 3.8
Classifier: Programming Language :: Python :: 3.9
Classifier: Framework :: Django
Requires-Dist: knox
Requires-Dist: djangorestframework
Requires-Dist: django (>=2.2)
Requires-Dist: jinja2
Requires-Dist: boto3
